my_libs
