Metadata-Version: 2.1
Name: my-libs-py
Version: 0.0.6
Summary: Wrapper para fins de estudo e cases de projetos pessoais
Author: Felipe Pegoraro
Author-email: felipepegoraro93@gmail.com
License: MIT License
Keywords: libs python
License-File: LICENCE
